[
    {
        "id": "1",
        "title": "Macarrão mediterrâneo",
        "description": "Macarrão spaghetti com frutos-do-mar e especíarias, especialidade da cozinha. Atenção: Contém camarão e outros frutos-do-mar!",
        "photo": "/assets/macarrao_mediterraneo.png",
        "git_path": "url"
    },
    {
        "id": "2",
        "title": "Macarrão da casa",
        "description": "Macarrão com frutos-do-mar e especíarias, especialidade da cozinha. Atenção: Contém camarão e outros frutos-do-mar!",
        "photo": "/assets/macarrao_da_casa.png",
        "git_path": "url"
    },
    {
        "id": "3",
        "title": "Macarrão com chilli",
        "description": "Macarrão fetuccine com molho de chilli e especiárias.",
        "photo": "/assets/macarrao_com_chilli.png",
        "git_path": "url"
    },
    {
        "id": "4",
        "title": "Salada da casa com salmão grelhado",
        "description": "Salada da casa (alface, rúcula, cenoura) com salmão.",
        "photo": "/assets/salada_da_casa.png",
        "git_path": "url"
    },
    {
        "id": "5",
        "title": "Bife com batatas",
        "description": "Bife de boi (150g) na chapa, com batatas fritas. Acompanha arroz e molhos.",
        "photo": "/assets/bife_com_batatas.png",
        "git_path": "url"
    },
    {
        "id": "6",
        "title": "Picanha picada com legumes e massa",
        "description": "400g de picanha picada, com legumes grelhados e massa escolhida pelo cliente.",
        "photo": "/assets/picanha_picada.png",
        "git_path": "url"
    }
]
